CHANGES.txt
LICENSE.txt
MANIFEST.in
README.txt
bootstrap.py
setup.py
src/j01/__init__.py
src/j01.livesearch.egg-info/PKG-INFO
src/j01.livesearch.egg-info/SOURCES.txt
src/j01.livesearch.egg-info/dependency_links.txt
src/j01.livesearch.egg-info/namespace_packages.txt
src/j01.livesearch.egg-info/not-zip-safe
src/j01.livesearch.egg-info/requires.txt
src/j01.livesearch.egg-info/top_level.txt
src/j01/livesearch/__init__.py
src/j01/livesearch/browser.py
src/j01/livesearch/interfaces.py
src/j01/livesearch/jsonrpc.py
src/j01/livesearch/js/j01.livesearch.js